sepa_generator/__init__.py
sepa_generator/builder.py
sepa_generator/core.py
sepa_generator/definitions.py
sepa_generator-0.2.1.dist-info/METADATA
sepa_generator-0.2.1.dist-info/RECORD
sepa_generator-0.2.1.dist-info/WHEEL
sepa_generator-0.2.1.dist-info/top_level.txt
