Metadata-Version: 2.1
Name: sepa-generator
Version: 0.2.1
Summary: Simple Python library for creating SEPA Credit Transfer XML documents
Home-page: https://github.com/boris-savic/python_sepa
Author: Boris Savic
Author-email: boris70@gmail.com
License: UNKNOWN
Download-URL: https://github.com/boris-savic/python_sepa/tarball/0.2.1
Keywords: python sepa_generator generator,SEPA,SEPA Credit Transfer,SEPACreditTransfer
Platform: UNKNOWN
Requires-Dist: lxml (>=3.8.0)
Requires-Dist: pytz (>=2017.2)
